nilearn_extra/__init__.py
nilearn_extra/connectome/__init__.py
nilearn_extra/connectome/_chatterjee.py
nilearn_extra/connectome/_transfer_entropy.py
nilearn_extra/connectome/extra_connectivity_matrices.py
nilearn_extra-0.1.1.dist-info/LICENSE
nilearn_extra-0.1.1.dist-info/WHEEL
nilearn_extra-0.1.1.dist-info/METADATA
nilearn_extra-0.1.1.dist-info/RECORD
