Metadata-Version: 2.1
Name: nilearn-extra
Version: 0.1.1
Summary: Drop-in extra functionalities for nilearn (statistics for neuroimaging in Python)
Home-page: https://github.com/morteza/nilearn-extra
License: BSD 3-Clause
Keywords: neuroimaging,nilearn,machine learning
Author: Morteza Ansarinia
Author-email: ansarinia@me.com
Requires-Python: >=3.9,<3.11
Classifier: License :: Other/Proprietary License
Classifier: Operating System :: OS Independent
Classifier: Programming Language :: Python :: 3
Classifier: Programming Language :: Python :: 3.10
Classifier: Programming Language :: Python :: 3.9
Classifier: Topic :: Software Development :: Libraries :: Python Modules
Requires-Dist: nilearn (>=0.9.1,<0.10.0)
Requires-Dist: scipy (>=1.8,<2.0)
Project-URL: Repository, https://github.com/morteza/nilearn-extra
